{"name":"Overview","date":"2018-05-22T14:40:25.000Z","source":"ACAPS","language":"en","url":"https://www.acaps.org/country/south-sudan","main":"<p>Clashes between government and opposition forces are reported in Upper Nile, Jonglei, Central and Eastern Equatoria, and Western Bahr el Ghazal, causing widespread human rights violations, large scale internal displacement and refugee outflow towards Sudan and Uganda. Violence against aid workers has escalated, hampering aid delivery in conflict-affected areas.</p><p>Food insecurity continues to affect 5.69 million people. Critical malnutrition levels are reported in Unity, Western Equatoria, Western Bahr el Ghazal, Eastern Equatoria and Jonglei.&nbsp;</p><p>INFORM measures South Sudan&#39;s risk of humanitarian crisis and disaster for 2018&nbsp;to be extremely high, at 9/10, an increase from 8.8/10 in 2017 and 8.3/10 in 2016. South Sudan&#39;s vulnerability is measured at 9.3/10.</p>","latest_developments_past":"<p><strong>22/05</strong>: Household-level <a href=\"https://www.acaps.org/country/south-sudan/crisis-analysis#container-874-datacard-44863\">food insecurity at IPC Phase 5 (Catastrophe)</a> is currently possible in Pibor (Jonglei) and Kapoeta East (Eastern Equatoria). Cattle raiding is disrupting livelihoods and humanitarian access is restricted.&nbsp;<a href=\"#\" title=\"FEWSNET 04/2018 http://fews.net/east-africa/south-sudan/food-security-outlook-update/april-2018\">?</a></p>","latest_developments_upcoming":""}