{"name":"Overview","date":"2018-01-16T07:31:04.000Z","source":"ACAPS","language":"en","url":"https://www.acaps.org/country/sudan","main":"<p>Protracted insurgencies are being waged by armed groups across Darfur, and persistent conflict situations in South Kordofan and Blue Nile cause high levels of insecurity. Darfur has been the scene of conflict for over a decade, while violence in Blue Nile and South Kordofan increased significantly after South Sudan gained independence in 2011. &nbsp;</p><p>Humanitarian access to conflict zones is severely restricted and remains so despite efforts of the AU and UN to broker a peace agreement and ensure increased humanitarian access. &nbsp;Violence, food insecurity, malnutrition, and lack of access to basic services have caused large-scale internal displacement. &nbsp;</p><p>According to INFORM, Sudan is at high risk of being overwhelmed by humanitarian crises and disasters (7.6/10). Hazard, vulnerability, and a lack of coping capacity are at alarming rates of 8.1/10, 6.9/10, and 7.9/10.&nbsp;<a href=\"http://www.inform-index.org/Countries/Country-Profile-Map\" target=\"_blank\" title=\"Inform 2018\">?</a></p>","latest_developments_past":"<p><strong>07/01:</strong>&nbsp;The removal of wheat subsidies as&nbsp;part of austerity measures<a href=\"https://www.acaps.org/country/sudan/crisis-analysis#datacard-39886\"> doubled bread prices </a>&nbsp;in early-January 2018 and caused protests in Khartoum, Nyala, Geneina, and al-Damazi as people have expressed worries that the 25% national inflation rate is making bread and other food unaffordable.<a href=\"https://www.reuters.com/article/us-sudan-protests/student-killed-opposition-leader-detained-as-bread-protests-grip-sudan-idUSKBN1EW0R6\" target=\"_blank\" title=\"Reuters 07/01/2018\">?</a><a href=\"http://www.sudantribune.com/spip.php?article64445\" target=\"_blank\" title=\"Sudan Tribune 07/01/2018\">?</a>&nbsp;</p>","latest_developments_upcoming":""}