{"appeals":[{"id":589,"source":"FTS","year":2017,"name":"Kenya Flash Appeal 2017","type":"Flash appeal","received":559231,"required":165767183,"percentage":0,"countries":["KEN"],"donors":{"total":559231,"grouping":[{"type":"Sweden, Government of","amount":559231}]},"clusters":[{"name":"Health","funding":0,"current_requirement":15000000},{"name":"Education","funding":0,"current_requirement":5921500},{"name":"Protection","funding":0,"current_requirement":3100000},{"name":"Agriculture and livelihood","funding":0,"current_requirement":30000000},{"name":"Food security","funding":0,"current_requirement":39300000},{"name":"Early recovery","funding":0,"current_requirement":8110000},{"name":"Wash","funding":559231,"current_requirement":21102106},{"name":"Nutrition","funding":0,"current_requirement":43233577}]}]}