[{"name":"People in Need","value":"8400000","date":"2020-01-28T12:00:00Z","url":"https://m.reliefweb.int/report/3496498","source":"Government of Ethiopia","values":[{"value":"8400000","date":"2020-01-28T12:00:00Z","url":"https://m.reliefweb.int/report/3496498"},{"value":"8860000","date":"2019-10-21T12:00:00Z","url":"https://m.reliefweb.int/report/3357763"},{"value":"8860000","date":"2019-03-07T12:00:00Z","url":"https://m.reliefweb.int/report/3024633"},{"value":"8000000","date":"2018-12-04T12:00:00Z","url":"https://m.reliefweb.int/report/2900688"},{"value":"7900000","date":"2018-06-19T12:00:00Z","url":"https://m.reliefweb.int/report/2659134"},{"value":"7880000","date":"2018-03-09T12:00:00Z","url":"https://m.reliefweb.int/report/2504064"},{"value":"7000000","date":"2017-12-01T12:00:00Z","url":"https://m.reliefweb.int/report/2354269"},{"value":"8500000","date":"2017-08-08T12:00:00Z","url":"http://m.reliefweb.int/report/2161734"},{"value":"5600000","date":"2017-06-21T12:00:00Z","url":"http://m.reliefweb.int/report/2087129"},{"value":"5600000","date":"2017-01-17T12:00:00Z","url":"http://m.reliefweb.int/report/1860924"},{"value":"9700000","date":"2016-08-12T12:00:00Z","url":"http://m.reliefweb.int/report/1651061"},{"value":"10200000","date":"2016-01-01T12:00:00Z","url":"http://m.reliefweb.int/report/1302911"},{"value":"4500000","date":"2015-08-15T12:00:00Z","url":"http://m.reliefweb.int/report/1131896"},{"value":"2900000","date":"2015-01-31T12:00:00Z","url":"http://m.reliefweb.int/report/879316"},{"value":"3200000","date":"2014-09-30T12:00:00Z","url":"http://m.reliefweb.int/report/877891"},{"value":"2700000","date":"2014-01-28T12:00:00Z","url":"http://m.reliefweb.int/report/632821"},{"value":"2700000","date":"2013-08-14T12:00:00Z","url":"http://m.reliefweb.int/report/595857"},{"value":"2400000","date":"2013-02-28T12:00:00Z","url":"http://m.reliefweb.int/report/560237"},{"value":"3760000","date":"2012-08-16T12:00:00Z","url":"http://m.reliefweb.int/report/518162"}],"description":"","language":"en"},{"name":"People Targeted for Assistance","value":"7000000","date":"2020-01-28T12:00:00Z","url":"https://m.reliefweb.int/report/3496498","source":"Government of Ethiopia","values":[{"value":"7000000","date":"2020-01-28T12:00:00Z","url":"https://m.reliefweb.int/report/3496498"},{"value":"7800000","date":"2019-10-21T12:00:00Z","url":"https://m.reliefweb.int/report/3357763"},{"value":"8300000","date":"2019-03-07T12:00:00Z","url":"https://m.reliefweb.int/report/3024633"},{"value":"8000000","date":"2018-12-04T12:00:00Z","url":"https://m.reliefweb.int/report/2900688"},{"value":"7900000","date":"2018-06-19T12:00:00Z","url":"https://m.reliefweb.int/report/2659134"},{"value":"7000000","date":"2017-12-01T12:00:00Z","url":"https://m.reliefweb.int/report/2354269"},{"value":"8500000","date":"2017-08-08T12:00:00Z","url":"http://m.reliefweb.int/report/2161734"},{"value":"5600000","date":"2017-06-21T12:00:00Z","url":"http://m.reliefweb.int/report/2087129"},{"value":"5600000","date":"2017-01-17T12:00:00Z","url":"http://m.reliefweb.int/report/1860924"},{"value":"9700000","date":"2016-08-12T12:00:00Z","url":"http://m.reliefweb.int/report/1651061"},{"value":"10200000","date":"2015-12-11T12:00:00Z","url":"http://m.reliefweb.int/report/1302911"}],"description":"","language":"en"},{"name":"Children in Need of Treatment for Severe Acute Malnutrition","value":"609961","date":"2019-10-21T12:00:00Z","url":"https://m.reliefweb.int/report/3357763","source":"OCHA","values":[{"value":"609961","date":"2019-10-21T12:00:00Z","url":"https://m.reliefweb.int/report/3357763"},{"value":"609961","date":"2019-03-07T12:00:00Z","url":"https://m.reliefweb.int/report/3024633"},{"value":"370000","date":"2018-10-09T12:00:00Z","url":"https://m.reliefweb.int/report/2822274"},{"value":"350111","date":"2018-05-28T12:00:00Z","url":"https://m.reliefweb.int/report/2620909"},{"value":"350111","date":"2018-03-09T12:00:00Z","url":"https://m.reliefweb.int/report/2504064"},{"value":"303000","date":"2017-01-17T12:00:00Z","url":"https://m.reliefweb.int/report/1860924"},{"value":"400000","date":"2015-12-07T12:00:00Z","url":"https://m.reliefweb.int/report/1300026"}],"description":"","language":"en"},{"name":"Children in Need","value":"4240000","date":"2019-12-03T12:00:00Z","url":"https://m.reliefweb.int/report/3425693","source":"UNICEF","values":[{"value":"4240000","date":"2019-12-03T12:00:00Z","url":"https://m.reliefweb.int/report/3425693"},{"value":"4200000","date":"2019-01-30T12:00:00Z","url":"https://m.reliefweb.int/report/2971573"},{"value":"4300000","date":"2018-08-31T12:00:00Z","url":"https://m.reliefweb.int/report/2801159"},{"value":"3500000","date":"2017-12-27T12:00:00Z","url":"https://m.reliefweb.int/report/2400904"},{"value":"4800000","date":"2017-01-09T12:00:00Z","url":"https://m.reliefweb.int/report/1850609"},{"value":"5700000","date":"2016-01-26T12:00:00Z","url":"https://m.reliefweb.int/report/1362341"},{"value":"1200000","date":"2015-01-29T12:00:00Z","url":"https://m.reliefweb.int/report/827011"}],"description":"","language":"en"},{"name":"People in Food Crisis/Emergency (IPC phase 3+)","value":"6689777","date":"2019-11-20T12:00:00Z","url":"https://m.reliefweb.int/report/3403688","source":"IPC","values":[{"value":"6689777","date":"2019-11-20T12:00:00Z","url":"https://m.reliefweb.int/report/3403688"},{"value":"7966980","date":"2019-07-31T12:00:00Z","url":"https://m.reliefweb.int/report/3403688"}],"description":"","language":"en"},{"name":"IDPs","value":"1642458","date":"2019-08-31T12:00:00Z","url":"https://m.reliefweb.int/report/3362453","source":"IOM","values":[{"value":"1642458","date":"2019-08-31T12:00:00Z","url":"https://m.reliefweb.int/report/3362453"},{"value":"2235290","date":"2019-06-30T12:00:00Z","url":"https://m.reliefweb.int/report/3362453"},{"value":"3043695","date":"2019-04-30T12:00:00Z","url":"https://m.reliefweb.int/report/3362453"},{"value":"3039590","date":"2019-02-28T12:00:00Z","url":"https://m.reliefweb.int/report/3362453"},{"value":"2893229","date":"2018-12-31T12:00:00Z","url":"https://m.reliefweb.int/report/3362453"},{"value":"2679035","date":"2018-10-31T12:00:00Z","url":"https://m.reliefweb.int/report/3362453"},{"value":"2783675","date":"2018-08-31T12:00:00Z","url":"https://m.reliefweb.int/report/3362453"},{"value":"1776685","date":"2018-06-30T12:00:00Z","url":"https://m.reliefweb.int/report/3362453"}],"description":"","language":"en"},{"name":"Conflict Affected IDPs","value":"1645867","date":"2019-06-01T12:00:00Z","url":"https://m.reliefweb.int/report/3256764","source":"IOM","values":[{"value":"1645867","date":"2019-06-01T12:00:00Z","url":"https://m.reliefweb.int/report/3256764"},{"value":"1663396","date":"2019-02-28T12:00:00Z","url":"https://m.reliefweb.int/report/3053708"},{"value":"1773482","date":"2018-12-31T12:00:00Z","url":"https://m.reliefweb.int/report/2952004"},{"value":"1472209","date":"2018-10-31T12:00:00Z","url":"https://m.reliefweb.int/report/2877958"},{"value":"1453422","date":"2018-08-31T12:00:00Z","url":"https://m.reliefweb.int/report/2852073"},{"value":"1204577","date":"2018-06-30T12:00:00Z","url":"https://m.reliefweb.int/report/2698524"},{"value":"1073764","date":"2018-04-30T12:00:00Z","url":"https://m.reliefweb.int/report/2630769"},{"value":"1216793","date":"2018-02-28T12:00:00Z","url":"https://m.reliefweb.int/report/2506074"},{"value":"1078429","date":"2017-12-31T12:00:00Z","url":"https://m.reliefweb.int/report/2446104"}],"description":"","language":"en"},{"name":"Climate Induced IDPs","value":"518334","date":"2019-06-01T12:00:00Z","url":"https://m.reliefweb.int/report/3256764","source":"IOM","values":[{"value":"518334","date":"2019-06-01T12:00:00Z","url":"https://m.reliefweb.int/report/3256764"},{"value":"508723","date":"2019-02-28T12:00:00Z","url":"https://m.reliefweb.int/report/3053708"},{"value":"498417","date":"2018-12-31T12:00:00Z","url":"https://m.reliefweb.int/report/2952004"},{"value":"531001","date":"2018-10-31T12:00:00Z","url":"https://m.reliefweb.int/report/2877958"},{"value":"541490","date":"2018-08-31T12:00:00Z","url":"https://m.reliefweb.int/report/2852073"},{"value":"536321","date":"2018-06-30T12:00:00Z","url":"https://m.reliefweb.int/report/2698524"},{"value":"488090","date":"2018-04-30T12:00:00Z","url":"https://m.reliefweb.int/report/2630769"},{"value":"494256","date":"2018-02-28T12:00:00Z","url":"https://m.reliefweb.int/report/2506074"},{"value":"528658","date":"2017-12-31T12:00:00Z","url":"https://m.reliefweb.int/report/2446104"}],"description":"","language":"en"},{"name":"IDPs by Other Factors","value":"71089","date":"2019-06-01T12:00:00Z","url":"https://m.reliefweb.int/report/3256764","source":"IOM","values":[{"value":"71089","date":"2019-06-01T12:00:00Z","url":"https://m.reliefweb.int/report/3256764"},{"value":"54990","date":"2019-02-28T12:00:00Z","url":"https://m.reliefweb.int/report/3053708"},{"value":"61037","date":"2018-12-31T12:00:00Z","url":"https://m.reliefweb.int/report/2952004"},{"value":"72068","date":"2018-10-31T12:00:00Z","url":"https://m.reliefweb.int/report/2877958"},{"value":"40264","date":"2018-08-31T12:00:00Z","url":"https://m.reliefweb.int/report/2852073"},{"value":"35787","date":"2018-06-30T12:00:00Z","url":"https://m.reliefweb.int/report/2698524"},{"value":"51582","date":"2018-04-30T12:00:00Z","url":"https://m.reliefweb.int/report/2630769"},{"value":"32537","date":"2018-02-28T12:00:00Z","url":"https://m.reliefweb.int/report/2506074"},{"value":"89058","date":"2017-12-31T12:00:00Z","url":"https://m.reliefweb.int/report/2446104"}],"description":"","language":"en"},{"name":"Refugees & Asylum-Seekers in Ethiopia","value":"705820","date":"2019-10-31T12:00:00Z","url":"https://m.reliefweb.int/report/3386128","source":"UNHCR","values":[{"value":"705820","date":"2019-10-31T12:00:00Z","url":"https://m.reliefweb.int/report/3386128"},{"value":"702145","date":"2019-09-30T12:00:00Z","url":"https://m.reliefweb.int/report/3339623"},{"value":"655105","date":"2019-07-29T12:00:00Z","url":"https://m.reliefweb.int/report/3334138"}],"description":"","language":"en"},{"name":"Refugee & Asylum-Seeker Arrivals in Ethiopia (Cumulative per year)","value":"80776","date":"2019-10-31T12:00:00Z","url":"https://m.reliefweb.int/report/3386128","source":"UNHCR","values":[{"value":"80776","date":"2019-10-31T12:00:00Z","url":"https://m.reliefweb.int/report/3386128"}],"description":"","language":"en"},{"name":"Refugee & Asylum-Seeker Arrivals in Ethiopia (per month)","value":"7947","date":"2019-10-31T12:00:00Z","url":"https://m.reliefweb.int/report/3386128","source":"UNHCR","values":[{"value":"7947","date":"2019-10-31T12:00:00Z","url":"https://m.reliefweb.int/report/3386128"},{"value":"7456","date":"2019-09-30T12:00:00Z","url":"https://m.reliefweb.int/report/3386128"},{"value":"7966","date":"2019-08-31T12:00:00Z","url":"https://m.reliefweb.int/report/3386128"},{"value":"11079","date":"2019-07-31T12:00:00Z","url":"https://m.reliefweb.int/report/3386128"},{"value":"11214","date":"2019-06-30T12:00:00Z","url":"https://m.reliefweb.int/report/3386128"},{"value":"6744","date":"2019-05-31T12:00:00Z","url":"https://m.reliefweb.int/report/3386128"},{"value":"6996","date":"2019-04-30T12:00:00Z","url":"https://m.reliefweb.int/report/3386128"},{"value":"8910","date":"2019-03-31T12:00:00Z","url":"https://m.reliefweb.int/report/3386128"},{"value":"6261","date":"2019-02-28T12:00:00Z","url":"https://m.reliefweb.int/report/3386128"},{"value":"6203","date":"2019-01-31T12:00:00Z","url":"https://m.reliefweb.int/report/3386128"}],"description":"","language":"en"},{"name":"S. Sudanese Refugees & Asylum-Seekers in Ethiopia","value":"320957","date":"2019-11-30T12:00:00Z","url":"https://m.reliefweb.int/report/3477328","source":"UNHCR","values":[{"value":"320957","date":"2019-11-30T12:00:00Z","url":"https://m.reliefweb.int/report/3477328"},{"value":"329785","date":"2019-10-31T12:00:00Z","url":"https://m.reliefweb.int/report/3386128"},{"value":"314546","date":"2019-09-30T12:00:00Z","url":"https://m.reliefweb.int/report/3339623"},{"value":"303773","date":"2019-07-29T12:00:00Z","url":"https://m.reliefweb.int/report/3334138"}],"description":"","language":"en"},{"name":"S. Sudanese Refugee Arrivals in Ethiopia (per year)","value":"5517","date":"2019-11-30T12:00:00Z","url":"https://m.reliefweb.int/report/3477328","source":"UNHCR","values":[{"value":"5517","date":"2019-11-30T12:00:00Z","url":"https://m.reliefweb.int/report/3477328"}],"description":"","language":"en"},{"name":"S. Sudanese Refugee Arrivals in Gambella (per year)","value":"8231","date":"2019-12-31T12:00:00Z","url":"https://m.reliefweb.int/report/3471628","source":"UNHCR","values":[{"value":"8231","date":"2019-12-31T12:00:00Z","url":"https://m.reliefweb.int/report/3471628"},{"value":"21971","date":"2018-12-31T12:00:00Z","url":"https://m.reliefweb.int/report/3025133"},{"value":"67759","date":"2017-12-31T12:00:00Z","url":"https://m.reliefweb.int/report/2519669"},{"value":"54739","date":"2016-12-31T12:00:00Z","url":"https://m.reliefweb.int/report/2519669"},{"value":"28509","date":"2015-12-31T12:00:00Z","url":"https://m.reliefweb.int/report/2519669"},{"value":"191698","date":"2014-12-31T12:00:00Z","url":"https://m.reliefweb.int/report/2519669"}],"description":"","language":"en"},{"name":"S. Sudanese Refugee Arrivals in Gambella (per month)","value":"2704","date":"2019-12-31T12:00:00Z","url":"https://m.reliefweb.int/report/3471628","source":"UNHCR","values":[{"value":"2704","date":"2019-12-31T12:00:00Z","url":"https://m.reliefweb.int/report/3471628"},{"value":"1669","date":"2019-11-30T12:00:00Z","url":"https://m.reliefweb.int/report/3439938"},{"value":"212","date":"2019-10-31T12:00:00Z","url":"https://m.reliefweb.int/report/3388723"},{"value":"177","date":"2019-09-30T12:00:00Z","url":"https://m.reliefweb.int/report/3388723"},{"value":"250","date":"2019-08-31T12:00:00Z","url":"https://m.reliefweb.int/report/3388723"},{"value":"300","date":"2019-07-31T12:00:00Z","url":"https://m.reliefweb.int/report/3388723"},{"value":"91","date":"2019-06-30T12:00:00Z","url":"https://m.reliefweb.int/report/3388723"},{"value":"260","date":"2019-05-31T12:00:00Z","url":"https://m.reliefweb.int/report/3388723"},{"value":"276","date":"2019-04-30T12:00:00Z","url":"https://m.reliefweb.int/report/3388723"},{"value":"174","date":"2019-03-31T12:00:00Z","url":"https://m.reliefweb.int/report/3388723"},{"value":"103","date":"2019-02-28T12:00:00Z","url":"https://m.reliefweb.int/report/3025133"},{"value":"2015","date":"2019-01-31T12:00:00Z","url":"https://m.reliefweb.int/report/3025133"},{"value":"3228","date":"2018-12-31T12:00:00Z","url":"https://m.reliefweb.int/report/3025133"},{"value":"1024","date":"2018-11-30T12:00:00Z","url":"https://m.reliefweb.int/report/3025133"},{"value":"82","date":"2018-10-31T12:00:00Z","url":"https://m.reliefweb.int/report/3025133"},{"value":"83","date":"2018-09-30T12:00:00Z","url":"https://m.reliefweb.int/report/3025133"},{"value":"40","date":"2018-08-31T12:00:00Z","url":"https://m.reliefweb.int/report/3025133"},{"value":"22","date":"2018-07-31T12:00:00Z","url":"https://m.reliefweb.int/report/3025133"},{"value":"885","date":"2018-06-30T12:00:00Z","url":"https://m.reliefweb.int/report/3025133"},{"value":"1841","date":"2018-05-31T12:00:00Z","url":"https://m.reliefweb.int/report/2642644"},{"value":"799","date":"2018-04-30T12:00:00Z","url":"https://m.reliefweb.int/report/2642644"},{"value":"3639","date":"2018-03-31T12:00:00Z","url":"https://m.reliefweb.int/report/2642644"},{"value":"4529","date":"2018-02-28T12:00:00Z","url":"https://m.reliefweb.int/report/2519669"},{"value":"5799","date":"2018-01-31T12:00:00Z","url":"https://m.reliefweb.int/report/2519669"},{"value":"931","date":"2017-12-31T12:00:00Z","url":"https://m.reliefweb.int/report/2519669"},{"value":"466","date":"2017-11-30T12:00:00Z","url":"https://m.reliefweb.int/report/2519669"},{"value":"151","date":"2017-10-31T12:00:00Z","url":"https://m.reliefweb.int/report/2519669"},{"value":"24911","date":"2017-09-30T12:00:00Z","url":"https://m.reliefweb.int/report/2519669"},{"value":"4354","date":"2017-08-31T12:00:00Z","url":"https://m.reliefweb.int/report/2519669"},{"value":"525","date":"2017-07-31T12:00:00Z","url":"https://m.reliefweb.int/report/2519669"},{"value":"1463","date":"2017-06-30T12:00:00Z","url":"https://m.reliefweb.int/report/2519669"},{"value":"1411","date":"2017-05-31T12:00:00Z","url":"https://m.reliefweb.int/report/2519669"},{"value":"8514","date":"2017-04-30T12:00:00Z","url":"https://m.reliefweb.int/report/2519669"},{"value":"16274","date":"2017-03-31T12:00:00Z","url":"https://m.reliefweb.int/report/2519669"}],"description":"","language":"en"},{"name":"S. Sudanese Refugee Arrivals in Gambella (per month)","value":"103","date":"2019-02-28T12:00:00Z","url":"https://m.reliefweb.int/report/3025133","source":"UNHCR","values":[{"value":"103","date":"2019-02-28T12:00:00Z","url":"https://m.reliefweb.int/report/3025133"},{"value":"2015","date":"2019-01-31T12:00:00Z","url":"https://m.reliefweb.int/report/3025133"},{"value":"3228","date":"2018-12-31T12:00:00Z","url":"https://m.reliefweb.int/report/3025133"},{"value":"1024","date":"2018-11-30T12:00:00Z","url":"https://m.reliefweb.int/report/3025133"},{"value":"82","date":"2018-10-31T12:00:00Z","url":"https://m.reliefweb.int/report/3025133"},{"value":"83","date":"2018-09-30T12:00:00Z","url":"https://m.reliefweb.int/report/3025133"},{"value":"40","date":"2018-08-31T12:00:00Z","url":"https://m.reliefweb.int/report/3025133"},{"value":"22","date":"2018-07-31T12:00:00Z","url":"https://m.reliefweb.int/report/3025133"},{"value":"885","date":"2018-06-30T12:00:00Z","url":"https://m.reliefweb.int/report/3025133"},{"value":"1841","date":"2018-05-31T12:00:00Z","url":"https://m.reliefweb.int/report/2642644"},{"value":"799","date":"2018-04-30T12:00:00Z","url":"https://m.reliefweb.int/report/2642644"},{"value":"3639","date":"2018-03-31T12:00:00Z","url":"https://m.reliefweb.int/report/2642644"},{"value":"4529","date":"2018-02-28T12:00:00Z","url":"https://m.reliefweb.int/report/2519669"},{"value":"5799","date":"2018-01-31T12:00:00Z","url":"https://m.reliefweb.int/report/2519669"},{"value":"931","date":"2017-12-31T12:00:00Z","url":"https://m.reliefweb.int/report/2519669"},{"value":"466","date":"2017-11-30T12:00:00Z","url":"https://m.reliefweb.int/report/2519669"},{"value":"151","date":"2017-10-31T12:00:00Z","url":"https://m.reliefweb.int/report/2519669"},{"value":"24911","date":"2017-09-30T12:00:00Z","url":"https://m.reliefweb.int/report/2519669"},{"value":"4354","date":"2017-08-31T12:00:00Z","url":"https://m.reliefweb.int/report/2519669"},{"value":"525","date":"2017-07-31T12:00:00Z","url":"https://m.reliefweb.int/report/2519669"},{"value":"1463","date":"2017-06-30T12:00:00Z","url":"https://m.reliefweb.int/report/2519669"},{"value":"1411","date":"2017-05-31T12:00:00Z","url":"https://m.reliefweb.int/report/2519669"},{"value":"8514","date":"2017-04-30T12:00:00Z","url":"https://m.reliefweb.int/report/2519669"},{"value":"16274","date":"2017-03-31T12:00:00Z","url":"https://m.reliefweb.int/report/2519669"}],"description":"","language":"en"},{"name":"Somali Refugees & Asylum-Seekers in Ethiopia","value":"186874","date":"2019-10-31T12:00:00Z","url":"https://m.reliefweb.int/report/3386128","source":"UNHCR","values":[{"value":"186874","date":"2019-10-31T12:00:00Z","url":"https://m.reliefweb.int/report/3386128"},{"value":"181686","date":"2019-09-30T12:00:00Z","url":"https://m.reliefweb.int/report/3339623"},{"value":"175961","date":"2019-07-29T12:00:00Z","url":"https://m.reliefweb.int/report/3334138"}],"description":"","language":"en"},{"name":"Eritrean Refugees & Asylum-Seekers in Ethiopia","value":"140602","date":"2019-10-31T12:00:00Z","url":"https://m.reliefweb.int/report/3386128","source":"UNHCR","values":[{"value":"140602","date":"2019-10-31T12:00:00Z","url":"https://m.reliefweb.int/report/3386128"},{"value":"146690","date":"2019-09-30T12:00:00Z","url":"https://m.reliefweb.int/report/3339623"},{"value":"100566","date":"2019-07-29T12:00:00Z","url":"https://m.reliefweb.int/report/3334138"}],"description":"","language":"en"},{"name":"Sudanese Refugees and Asylum-seekers in Ethiopia","value":"41314","date":"2019-10-31T12:00:00Z","url":"https://m.reliefweb.int/report/3386128","source":"UNHCR","values":[{"value":"41314","date":"2019-10-31T12:00:00Z","url":"https://m.reliefweb.int/report/3386128"},{"value":"51855","date":"2019-09-30T12:00:00Z","url":"https://m.reliefweb.int/report/3334138"},{"value":"50777","date":"2019-07-29T12:00:00Z","url":"https://m.reliefweb.int/report/3334138"}],"description":"","language":"en"},{"name":"Yemeni Refugees and Asylum-seekers in Ethiopia","value":"1382","date":"2019-10-31T12:00:00Z","url":"https://m.reliefweb.int/report/3386128","source":"UNHCR","values":[{"value":"1382","date":"2019-10-31T12:00:00Z","url":"https://m.reliefweb.int/report/3386128"},{"value":"1378","date":"2019-09-30T12:00:00Z","url":"https://m.reliefweb.int/report/3334138"}],"description":"","language":"en"},{"name":"Total Cholera Cases (since May 2019)","value":"2089","date":"2020-01-20T12:00:00Z","url":"https://m.reliefweb.int/report/3494753","source":"WHO","values":[{"value":"2089","date":"2020-01-20T12:00:00Z","url":"https://m.reliefweb.int/report/3494753"},{"value":"2089","date":"2019-12-08T12:00:00Z","url":"https://m.reliefweb.int/report/3443423"},{"value":"1960","date":"2019-11-17T12:00:00Z","url":"https://m.reliefweb.int/report/3410323"},{"value":"1747","date":"2019-10-20T12:00:00Z","url":"https://m.reliefweb.int/report/3367963"},{"value":"1325","date":"2019-09-22T12:00:00Z","url":"https://m.reliefweb.int/report/3338438"},{"value":"1005","date":"2019-07-21T12:00:00Z","url":"https://m.reliefweb.int/report/3236018"},{"value":"642","date":"2019-06-30T12:00:00Z","url":"https://m.reliefweb.int/report/3215578"},{"value":"424","date":"2019-06-06T12:00:00Z","url":"https://m.reliefweb.int/report/3174249"},{"value":"176","date":"2019-05-17T12:00:00Z","url":"https://m.reliefweb.int/report/3145523"}],"description":"","language":"en"},{"name":"Cholera Confirmed Cases (since May 2019)","value":"60","date":"2020-01-20T12:00:00Z","url":"https://m.reliefweb.int/report/3494753","source":"WHO","values":[{"value":"60","date":"2020-01-20T12:00:00Z","url":"https://m.reliefweb.int/report/3494753"},{"value":"60","date":"2019-12-08T12:00:00Z","url":"https://m.reliefweb.int/report/3443423"},{"value":"60","date":"2019-11-17T12:00:00Z","url":"https://m.reliefweb.int/report/3410323"},{"value":"54","date":"2019-10-20T12:00:00Z","url":"https://m.reliefweb.int/report/3367963"},{"value":"53","date":"2019-09-22T12:00:00Z","url":"https://m.reliefweb.int/report/3338438"},{"value":"33","date":"2019-07-21T12:00:00Z","url":"https://m.reliefweb.int/report/3236018"},{"value":"20","date":"2019-06-30T12:00:00Z","url":"https://m.reliefweb.int/report/3215578"},{"value":"13","date":"2019-06-06T12:00:00Z","url":"https://m.reliefweb.int/report/3174249"},{"value":"1","date":"2019-05-17T12:00:00Z","url":"https://m.reliefweb.int/report/3145523"}],"description":"","language":"en"},{"name":"Cholera Deaths (since May 2019)","value":"21","date":"2020-01-20T12:00:00Z","url":"https://m.reliefweb.int/report/3494753","source":"WHO","values":[{"value":"21","date":"2020-01-20T12:00:00Z","url":"https://m.reliefweb.int/report/3494753"},{"value":"21","date":"2019-12-08T12:00:00Z","url":"https://m.reliefweb.int/report/3443423"},{"value":"21","date":"2019-11-17T12:00:00Z","url":"https://m.reliefweb.int/report/3410323"},{"value":"11","date":"2019-10-20T12:00:00Z","url":"https://m.reliefweb.int/report/3367963"},{"value":"11","date":"2019-09-22T12:00:00Z","url":"https://m.reliefweb.int/report/3338438"},{"value":"11","date":"2019-07-21T12:00:00Z","url":"https://m.reliefweb.int/report/3236018"}],"description":"","language":"en"},{"name":"New IDPs by Conflict (per year)","value":"522000","date":"2019-06-30T12:00:00Z","url":"https://m.reliefweb.int/report/3299773","source":"IDMC","values":[{"value":"522000","date":"2019-06-30T12:00:00Z","url":"https://m.reliefweb.int/report/3299773"},{"value":"2895000","date":"2018-12-31T12:00:00Z","url":"https://m.reliefweb.int/report/3121423"},{"value":"725000","date":"2017-12-31T12:00:00Z","url":"https://m.reliefweb.int/report/2603634"},{"value":"296000","date":"2016-12-31T12:00:00Z","url":"https://m.reliefweb.int/report/2039684"},{"value":"56000","date":"2015-12-31T12:00:00Z","url":"https://m.reliefweb.int/report/1520416"}],"description":"","language":"en"},{"name":"New IDPs by Natural Disasters (per year)","value":"233000","date":"2019-06-30T12:00:00Z","url":"https://m.reliefweb.int/report/3299773","source":"IDMC","values":[{"value":"233000","date":"2019-06-30T12:00:00Z","url":"https://m.reliefweb.int/report/3299773"},{"value":"296000","date":"2018-12-31T12:00:00Z","url":"https://m.reliefweb.int/report/3121423"},{"value":"434000","date":"2017-12-31T12:00:00Z","url":"https://m.reliefweb.int/report/2603634"},{"value":"347000","date":"2016-12-31T12:00:00Z","url":"https://m.reliefweb.int/report/2039684"},{"value":"104000","date":"2015-12-31T12:00:00Z","url":"https://m.reliefweb.int/report/1520416"}],"description":"","language":"en"},{"name":"People Received WFP Food Assistance (per month)","value":"2300000","date":"2019-12-31T12:00:00Z","url":"https://m.reliefweb.int/report/3495363","source":"WFP","values":[{"value":"2300000","date":"2019-12-31T12:00:00Z","url":"https://m.reliefweb.int/report/3495363"},{"value":"2300000","date":"2019-11-30T12:00:00Z","url":"https://m.reliefweb.int/report/3466653"},{"value":"2300000","date":"2019-10-31T12:00:00Z","url":"https://m.reliefweb.int/report/3455093"},{"value":"1600000","date":"2019-08-31T12:00:00Z","url":"https://m.reliefweb.int/report/3352538"},{"value":"4000000","date":"2019-07-31T12:00:00Z","url":"https://m.reliefweb.int/report/3294133"},{"value":"3000000","date":"2019-06-30T12:00:00Z","url":"https://m.reliefweb.int/report/3259973"},{"value":"2000000","date":"2019-05-31T12:00:00Z","url":"https://m.reliefweb.int/report/3232648"},{"value":"5000000","date":"2019-04-30T12:00:00Z","url":"https://m.reliefweb.int/report/3147368"},{"value":"4800000","date":"2018-12-31T12:00:00Z","url":"https://m.reliefweb.int/report/2980393"},{"value":"4430000","date":"2018-10-31T12:00:00Z","url":"https://m.reliefweb.int/report/2911188"},{"value":"3600000","date":"2018-09-30T12:00:00Z","url":"https://m.reliefweb.int/report/2860128"},{"value":"3500000","date":"2018-04-30T12:00:00Z","url":"https://m.reliefweb.int/report/2639829"},{"value":"5400000","date":"2018-03-31T12:00:00Z","url":"https://m.reliefweb.int/report/2590319"}],"description":"","language":"en"}]