[{"name":"Health and Nutrition","funding":3744075,"current_requirement":18328004},{"name":"Shelter NFIs","funding":24174458,"current_requirement":103615967},{"name":"Coordination and Support Services","funding":9772692,"current_requirement":19024998},{"name":"Education","funding":3956067,"current_requirement":20261954},{"name":"WASH","funding":3474556,"current_requirement":37191554},{"name":"Food Security","funding":127810373,"current_requirement":299683368},{"name":"Protection","funding":29840797,"current_requirement":53770798}]