{"name":"Resumen","date":null,"source":"","language":"sp","url":"http://m.reliefweb.int/report/1739411","main":"<p>El 16 de abril de 2016, un terremoto masivo de magnitud 7,8 en la escala de Richter sacudió la costa noroeste del Ecuador. El sismo dejó un balance de 671 personas fallecidas y más de 385.000 personas directamente afectadas.\nEl terremoto exacerbó factores preexistentes de vulnerabilidad social y económica en Esmeraldas y Manabí, las dos provincias más afectadas. Ya antes del evento, las provincias presentaban altos niveles de pobreza en 2014 (Esmeraldas 43,2% y Manabí 31,3%) y de ruralidad en 2010 (Esmeraldas 41,7% y Manabí 41,0%), según el Instituto Nacional de Estadística y Censos (INEC). Muchas de las viviendas adolecían de una falta de acceso regular a las redes de agua (43,4% en Esmeraldas y 49,1% en Manabí) y el acceso a saneamiento con alcantarillado es de 30,7% y 33,3%, respectivamente (INEC, 2010). </p>"}