[{"name":"Cccm/shelter/nfis","funding":0,"current_requirement":20300000},{"name":"Coordination and common services","funding":285786,"current_requirement":5100000},{"name":"Education","funding":0,"current_requirement":7100000},{"name":"Food security","funding":4000000,"current_requirement":50000000},{"name":"Health","funding":0,"current_requirement":16500000},{"name":"Nutrition","funding":0,"current_requirement":14100000},{"name":"Protection","funding":3676008,"current_requirement":20200000},{"name":"Wash","funding":0,"current_requirement":17000000}]