{"id":529,"source":"FTS","year":2017,"name":"occupied Palestinian territory 2017","type":"Humanitarian response plan","received":227969169,"required":551876643,"percentage":41,"countries":["PSE"],"donors":{"total":227969169,"grouping":[{"type":"Germany, Government of","amount":33235219},{"type":"Russian Federation, Government of","amount":2000000},{"type":"France, Government of","amount":1384575},{"type":"Slovenia, Government of","amount":53362},{"type":"Japan, Government of","amount":9244601},{"type":"Spain, Government of","amount":1292719},{"type":"European Commission's Humanitarian Aid and Civil Protection Department","amount":16424025},{"type":"UNICEF National Committee/France","amount":266809},{"type":"Switzerland, Government of","amount":4277617},{"type":"Sweden, Government of","amount":7958797},{"type":"Canada, Government of","amount":11804137},{"type":"Brazil, Government of","amount":200000},{"type":"Denmark, Government of","amount":1915832},{"type":"Not specified","amount":2118569},{"type":"Norway, Government of","amount":1250851},{"type":"United States of America, Government of","amount":110000000},{"type":"Finland, Government of","amount":4802561},{"type":"World Food Programme","amount":1709417},{"type":"Belgium, Government of","amount":3009082},{"type":"Estonia, Government of","amount":266809},{"type":"Australia, Government of","amount":1860119},{"type":"Islamic Development Bank","amount":1000000},{"type":"Italy, Government of","amount":1749511},{"type":"United Kingdom, Government of","amount":4000000},{"type":"Saudi Arabia (Kingdom of), Government of","amount":1000000},{"type":"Netherlands, Government of","amount":96148},{"type":"Ireland, Government of","amount":217155},{"type":"Private (individuals & organizations)","amount":99994},{"type":"Turkey, Government of","amount":500000},{"type":"American National Committee for UNRWA","amount":231260},{"type":"Kuwait Fund for Arab Economic Development","amount":4000000}]},"clusters":[{"name":"Health and Nutrition","funding":3744075,"current_requirement":18328004},{"name":"Shelter NFIs","funding":24174458,"current_requirement":103615967},{"name":"Coordination and Support Services","funding":9807902,"current_requirement":19024998},{"name":"Education","funding":3956067,"current_requirement":20261954},{"name":"WASH","funding":5090262,"current_requirement":37191554},{"name":"Food Security","funding":127810373,"current_requirement":299683368},{"name":"Protection","funding":30736653,"current_requirement":53770798}]}