{"id":664,"source":"FTS","year":2019,"name":"occupied Palestinian territory 2019  (part of 2018-2020 HRP)","type":"Humanitarian response plan","received":69975601,"required":350589271,"percentage":20,"countries":["PSE"],"donors":{"total":69975601,"grouping":[{"type":"UNICEF National Committee/Germany","amount":139557},{"type":"ACT Alliance / DanChurchAid","amount":38844},{"type":"Korea, Republic of, Government of","amount":125000},{"type":"Sweden, Government of","amount":7509193},{"type":"Central Emergency Response Fund","amount":8000000},{"type":"Switzerland, Government of","amount":3769251},{"type":"World Health Organization","amount":321543},{"type":"Canada, Government of","amount":3185463},{"type":"France, Government of","amount":1651340},{"type":"Denmark, Government of","amount":12557392},{"type":"Japan, Government of","amount":2533034},{"type":"Spain, Government of","amount":116550},{"type":"New Zealand, Government of","amount":25000},{"type":"Poland, Government of","amount":48437},{"type":"Netherlands, Government of","amount":141100},{"type":"Germany, Government of","amount":9749835},{"type":"European Commission's Humanitarian Aid and Civil Protection Department","amount":7729881},{"type":"Russian Federation, Government of","amount":2000000},{"type":"World Food Programme","amount":10000000},{"type":"Norway, Government of","amount":334181}]},"clusters":[{"name":"Coordination and Support Services","funding":2168512,"current_requirement":18489828},{"name":"Education","funding":1084335,"current_requirement":15318372},{"name":"Food Security Sector","funding":30855473,"current_requirement":205651973},{"name":"Health and Nutrition Cluster","funding":10663956,"current_requirement":31496553},{"name":"Protection","funding":4516846,"current_requirement":35883244},{"name":"Shelter/NFIs","funding":849308,"current_requirement":14294447},{"name":"WASH","funding":1391316,"current_requirement":29454854}]}