{"id":794,"source":"FTS","year":2019,"name":"Burkina Faso 2019","type":"Other","received":20371352,"required":100310030,"percentage":20,"countries":["BFA"],"donors":{"total":20371352,"grouping":[{"type":"Central Emergency Response Fund","amount":3002247},{"type":"European Commission's Humanitarian Aid and Civil Protection Department","amount":13125000},{"type":"Germany, Government of","amount":1799669},{"type":"Switzerland, Government of","amount":1153450},{"type":"Not specified","amount":996400},{"type":"Denmark, Government of","amount":294586}]},"clusters":[{"name":"Refugee Response","funding":0,"current_requirement":14100000},{"name":"Nutrition","funding":1930596,"current_requirement":29211710},{"name":"Food Security","funding":1927605,"current_requirement":15157000},{"name":"Preparation aux urgences","funding":0,"current_requirement":7241320},{"name":"Déplacement liés aux conflits","funding":2873218,"current_requirement":34600000}]}