{"total":35566320,"grouping":[{"type":"Development and Peace","amount":619674},{"type":"Sweden, Government of","amount":442527},{"type":"Germany, Government of","amount":2903600},{"type":"Central Emergency Response Fund","amount":11000000},{"type":"European Commission's Humanitarian Aid and Civil Protection Department","amount":14773115},{"type":"United States of America, Government of","amount":4998875},{"type":"Ireland, Government of","amount":593529},{"type":"Switzerland, Government of","amount":235000}]}