[{"name":"CCCM","funding":6697206,"current_requirement":18694000},{"name":"Coordination and Common Services","funding":18082380,"current_requirement":16089139},{"name":"ETC","funding":2482443,"current_requirement":2701261},{"name":"Education","funding":24903033,"current_requirement":69946877},{"name":"Emergency Livelihoods - Social Cohesion","funding":2524144,"current_requirement":20031306},{"name":"Food Security","funding":108817909,"current_requirement":235000000},{"name":"Health","funding":128373807,"current_requirement":109641716},{"name":"Logistics","funding":2464422,"current_requirement":11870344},{"name":"Multi-Purpose Cash Assistance","funding":18086204,"current_requirement":61398275},{"name":"Protection","funding":84581962,"current_requirement":106752112},{"name":"RRM","funding":1419012,"current_requirement":18000000},{"name":"Shelter - NFI","funding":88181848,"current_requirement":175313707},{"name":"WASH","funding":64137060,"current_requirement":139208327}]