{"highlights":{"funding_total":237471246},"appeals":[{"id":645,"source":"FTS","year":2018,"name":"Afghanistan 2018","type":"Humanitarian response plan","received":176865539,"required":546565000,"percentage":32,"countries":["AFG"],"donors":{"total":176865539,"grouping":[{"type":"Japan, Government of","amount":2935125},{"type":"United States of America, Government of","amount":48575000},{"type":"Denmark, Government of","amount":9163178},{"type":"Afghanistan, Government of","amount":209184},{"type":"Norway, Government of","amount":4500499},{"type":"Italy, Government of","amount":4303167},{"type":"Estonia, Government of","amount":60386},{"type":"Canada, Government of","amount":6987601},{"type":"Australia, Government of","amount":11385083},{"type":"Sweden, Government of","amount":10680794},{"type":"Germany, Government of","amount":3475994},{"type":"Bulgaria, Government of","amount":122700},{"type":"Switzerland, Government of","amount":3965513},{"type":"United Kingdom, Government of","amount":8156700},{"type":"United Nations Foundation","amount":2339},{"type":"United Nations Children's Fund","amount":12733462},{"type":"Not specified","amount":759376},{"type":"European Commission's Humanitarian Aid and Civil Protection Department","amount":26674842},{"type":"UNICEF National Committee/Canada","amount":10377},{"type":"Central Emergency Response Fund","amount":11937469},{"type":"Czech Republic, Government of","amount":228206},{"type":"Netherlands, Government of","amount":7427962},{"type":"Afghanistan Humanitarian Fund","amount":367000},{"type":"Ireland, Government of","amount":388889},{"type":"Qatar, Government of","amount":999960},{"type":"Kazakhstan, Government of","amount":50000},{"type":"Spain, Government of","amount":362319},{"type":"Swiss Solidarity","amount":402414}]},"clusters":[{"name":"Emergency Shelter and NFI","funding":4460107,"current_requirement":53000000},{"name":"Health","funding":13574083,"current_requirement":41600000},{"name":"Protection","funding":6831343,"current_requirement":66500000},{"name":"Nutrition","funding":21225245,"current_requirement":63365000},{"name":"Water, Sanitation and Hygiene","funding":16132852,"current_requirement":37700000},{"name":"Education in Emergencies WG","funding":3721368,"current_requirement":29700000},{"name":"Coordination","funding":15972835,"current_requirement":15900000},{"name":"Multi Purpose Cash","funding":2180094,"current_requirement":37100000},{"name":"Food Security and Agriculture","funding":36541292,"current_requirement":185300000},{"name":"Aviation","funding":925926,"current_requirement":16400000}]}]}