{"total":53407485,"grouping":[{"type":"Central Emergency Response Fund","amount":2712185},{"type":"African Development Bank","amount":1000000},{"type":"United States of America, Government of","amount":21561925},{"type":"Sweden, Government of","amount":950141},{"type":"United Kingdom, Government of","amount":4236679},{"type":"Not specified","amount":11454216},{"type":"Canada, Government of","amount":3193413},{"type":"Japan, Government of","amount":988803},{"type":"European Commission's Humanitarian Aid and Civil Protection Department","amount":740741},{"type":"Korea, Republic of, Government of","amount":3168000},{"type":"Private (individuals & organizations)","amount":2007853},{"type":"World Food Programme","amount":1161440},{"type":"Plan International","amount":212089},{"type":"UN Programme on HIV/AIDS","amount":20000}]}