{"total":23264912,"grouping":[{"type":"Japan, Government of","amount":7800000},{"type":"Monaco, Government of","amount":55866},{"type":"ECHO DFID contribution","amount":3813850},{"type":"Canada, Government of","amount":385208},{"type":"United States of America, Government of","amount":1501994},{"type":"UNICEF National Committee/United Kingdom","amount":101010},{"type":"World Food Programme","amount":2033000},{"type":"European Commission's Humanitarian Aid and Civil Protection Department","amount":3899517},{"type":"France, Government of","amount":557414},{"type":"European Commission","amount":1346630},{"type":"Private (individuals & organisations)","amount":425250},{"type":"Finland, Government of","amount":85155},{"type":"Not specified","amount":1260018}]}