{"highlights":{"funding_total":234199723},"appeals":[{"id":634,"source":"FTS","year":2018,"name":"Iraq 2018","type":"Humanitarian response plan","received":66556634,"required":568745625,"percentage":12,"countries":["IRQ"],"donors":{"total":66556634,"grouping":[{"type":"Germany, Government of","amount":15162976},{"type":"Qatar, Government of","amount":1000000},{"type":"Japan, Government of","amount":5699994},{"type":"Denmark, Government of","amount":1580590},{"type":"Iraq Humanitarian Fund","amount":3049095},{"type":"France, Government of","amount":613497},{"type":"Canada, Government of","amount":6785120},{"type":"Switzerland, Government of","amount":562963},{"type":"Ireland, Government of","amount":2453988},{"type":"Luxembourg, Government of","amount":370370},{"type":"Sweden, Government of","amount":2284264},{"type":"United Kingdom, Government of","amount":16783737},{"type":"Finland, Government of","amount":2219950},{"type":"United States of America, Government of","amount":4577121},{"type":"Belgium, Government of","amount":3412969}]},"clusters":[{"name":"CCCM","funding":0,"current_requirement":25039043},{"name":"Child Protection","funding":6584675,"current_requirement":22177235},{"name":"Coordination and Common Services","funding":3627364,"current_requirement":15000000},{"name":"ETC","funding":0,"current_requirement":1944505},{"name":"Education","funding":4891363,"current_requirement":38010386},{"name":"Emergency Livelihoods","funding":0,"current_requirement":3499826},{"name":"Food Security","funding":1999256,"current_requirement":150034721},{"name":"Gender-Based Violence","funding":299029,"current_requirement":16429551},{"name":"Health","funding":6559463,"current_requirement":67384095},{"name":"Logistics","funding":0,"current_requirement":2500000},{"name":"Multi-Purpose Cash Assistance","funding":700202,"current_requirement":59951760},{"name":"Protection","funding":3475106,"current_requirement":26393214},{"name":"RRM","funding":272999,"current_requirement":7000000},{"name":"Shelter - NFI","funding":5490090,"current_requirement":63381024},{"name":"WASH","funding":15491739,"current_requirement":70000265}]},{"id":658,"source":"FTS","year":2018,"name":"Syria regional refugee and resilience plan (3RP) 2018","type":"Regional response plan","received":1902986962,"required":5608951510,"percentage":34,"countries":["EGY","IRQ","JOR","LBN","TUR"],"donors":{"total":1902986962,"grouping":[{"type":"United Kingdom, Government of","amount":143477917},{"type":"United Nations Children's Fund","amount":320877198},{"type":"United States of America, Government of","amount":130182548},{"type":"Sweden, Government of","amount":6279450},{"type":"Luxembourg, Government of","amount":358423},{"type":"Italy, Government of","amount":7562243},{"type":"Private (individuals & organizations)","amount":18731409},{"type":"Estonia, Government of","amount":155134},{"type":"European Commission - EU Facility for Refugees in Turkey","amount":841228398},{"type":"Netherlands, Government of","amount":15644701},{"type":"Canada, Government of","amount":64638644},{"type":"Denmark, Government of","amount":2341881},{"type":"Norway, Government of","amount":18761840},{"type":"Germany, Government of","amount":146989845},{"type":"Switzerland, Government of","amount":5994628},{"type":"Russian Federation, Government of","amount":1570709},{"type":"Food & Agriculture Organization of the United Nations","amount":491388},{"type":"Kuwait, Government of","amount":6000000},{"type":"Japan, Government of","amount":34126841},{"type":"Not specified","amount":2731630},{"type":"France, Government of","amount":1124452},{"type":"European Commission","amount":86237612},{"type":"Qatar, Government of","amount":500000},{"type":"Korea, Republic of, Government of","amount":3307447},{"type":"Australia, Government of","amount":22878601},{"type":"Turkey, Government of","amount":90498},{"type":"UNICEF National Committee/Sweden","amount":95178},{"type":"UN Women","amount":135688},{"type":"United Nations High Commissioner for Refugees","amount":1000000},{"type":"UNICEF National Committee/Germany","amount":1066845},{"type":"Finland, Government of","amount":4788019},{"type":"Global Fund to Fight AIDS, Tuberculosis and Malaria","amount":1340168},{"type":"Mexico, Government of","amount":250000},{"type":"US Fund for UNICEF","amount":1495286},{"type":"United Arab Emirates, Government of","amount":99997},{"type":"UNICEF National Committee/Netherlands","amount":621118},{"type":"Saudi Arabia (Kingdom of), Government of","amount":930392},{"type":"Belgium, Government of","amount":1706485},{"type":"UNICEF National Committee/United Kingdom","amount":250000},{"type":"World Food Programme","amount":1325879},{"type":"UNICEF National Committee/Denmark","amount":584405},{"type":"KFW Development","amount":4760000},{"type":"Iceland, Government of","amount":254065}]},"clusters":[{"name":"Multi-sector","funding":1894801444,"current_requirement":5608951510}]}]}