{"highlights":{"funding_total":544155563},"appeals":[{"id":550,"source":"FTS","year":2017,"name":"Iraq 2017","type":"Humanitarian response plan","received":356951433,"required":984647064,"percentage":36,"countries":["IRQ"],"donors":{"total":356951433,"grouping":[{"type":"Canada, Government of","amount":36503723},{"type":"Japan, Government of","amount":52500125},{"type":"Switzerland, Government of","amount":3369950},{"type":"Germany, Government of","amount":33940964},{"type":"Slovenia, Government of","amount":32017},{"type":"Estonia, Government of","amount":160085},{"type":"Belgium, Government of","amount":3623189},{"type":"United Kingdom, Government of","amount":15319688},{"type":"Sweden, Government of","amount":11696554},{"type":"Finland, Government of","amount":3144183},{"type":"Austria, Government of","amount":3422033},{"type":"Norway, Government of","amount":1467561},{"type":"United States of America, Government of","amount":90163713},{"type":"Private (individuals & organizations)","amount":929250},{"type":"European Commission's Humanitarian Aid and Civil Protection Department","amount":58831614},{"type":"Netherlands, Government of","amount":5336179},{"type":"Ireland, Government of","amount":2123142},{"type":"Australia, Government of","amount":4464285},{"type":"Luxembourg, Government of","amount":583414},{"type":"OPEC Fund for International Development","amount":400000},{"type":"France, Government of","amount":3433726},{"type":"UNICEF National Committee/United Kingdom","amount":187087},{"type":"Slovakia, Government of","amount":54289},{"type":"Czech Republic, Government of","amount":156986},{"type":"Spain, Government of","amount":10672},{"type":"Liechtenstein, Government of","amount":99305},{"type":"Not specified","amount":9694},{"type":"World Food Programme","amount":14980000},{"type":"Andorra, Government of","amount":8004},{"type":"Central Emergency Response Fund","amount":10000001}]},"clusters":[{"name":"Coordination and Common Services","funding":12067955,"current_requirement":16089139},{"name":"RRM","funding":419012,"current_requirement":18000000},{"name":"WASH","funding":30337439,"current_requirement":139208327},{"name":"Multi-Purpose Cash Assistance","funding":11642021,"current_requirement":61398275},{"name":"Protection","funding":35066251,"current_requirement":106752112},{"name":"Shelter - NFI","funding":41814098,"current_requirement":175313707},{"name":"Education","funding":15921102,"current_requirement":69946877},{"name":"Logistics","funding":1149989,"current_requirement":11870344},{"name":"Food Security","funding":39471375,"current_requirement":235000000},{"name":"ETC","funding":0,"current_requirement":2701261},{"name":"Emergency Livelihoods - Social Cohesion","funding":3447263,"current_requirement":20031306},{"name":"Health","funding":53328657,"current_requirement":109641716},{"name":"CCCM","funding":1769300,"current_requirement":18694000}]},{"id":552,"source":"FTS","year":2017,"name":"Syria regional refugee and resilience plan (3RP) 2017","type":"Regional response plan","received":2006592746,"required":5575937077,"percentage":36,"countries":["JOR","TUR","LBN","IRQ","EGY","SYR"],"donors":{"total":2006592746,"grouping":[{"type":"Germany, Government of","amount":78101857},{"type":"Japan, Government of","amount":78753256},{"type":"United States of America, Government of","amount":438729990},{"type":"Belgium, Government of","amount":4019479},{"type":"Private (individuals & organizations)","amount":26812696},{"type":"UNICEF National Committee/Germany","amount":3344885},{"type":"UNICEF National Committee/Austria","amount":107914},{"type":"UNICEF National Committee/Belgium","amount":8272},{"type":"Norway, Government of","amount":36785091},{"type":"Canada, Government of","amount":58049319},{"type":"UNICEF National Committee/New Zealand","amount":6341},{"type":"UNICEF National Committee/Canada","amount":130810},{"type":"United Nations Children's Fund","amount":1906940},{"type":"UNICEF National Committee/Netherlands","amount":507988},{"type":"Italy, Government of","amount":3558034},{"type":"United Nations High Commissioner for Refugees","amount":1150957},{"type":"UNICEF National Committee/Australia","amount":333053},{"type":"UNICEF National Committee/Spain","amount":299798},{"type":"France, Government of","amount":17162588},{"type":"Denmark, Government of","amount":2194560},{"type":"UNICEF National Committee/France","amount":612394},{"type":"US Fund for UNICEF","amount":713341},{"type":"UNICEF National Committee/United Kingdom","amount":219684},{"type":"Switzerland, Government of","amount":5877961},{"type":"UNICEF National Committee/Japan","amount":3342048},{"type":"United Kingdom, Government of","amount":50472679},{"type":"Friends of UNFPA","amount":100080},{"type":"UNICEF National Committee/Italy","amount":101397},{"type":"Finland, Government of","amount":10779489},{"type":"China, Government of","amount":3500000},{"type":"Luxembourg, Government of","amount":692589},{"type":"Saudi Arabia (Kingdom of), Government of","amount":8328328},{"type":"Kuwait, Government of","amount":18803893},{"type":"United Arab Emirates, Government of","amount":40839},{"type":"Cyprus, Government of","amount":21930},{"type":"Spain, Government of","amount":1477474},{"type":"Australia, Government of","amount":11567745},{"type":"Malta, Government of","amount":10851},{"type":"Estonia, Government of","amount":282819},{"type":"Not specified","amount":507655229},{"type":"IKEA Foundation","amount":2326732},{"type":"Food & Agriculture Organization of the United Nations","amount":460000},{"type":"Global Fund to Fight AIDS, Tuberculosis and Malaria","amount":2690966},{"type":"Sweden, Government of","amount":15394575},{"type":"European Commission - EU Facility for Refugees in Turkey","amount":459012795},{"type":"European Commission's Humanitarian Aid and Civil Protection Department","amount":45343870},{"type":"INTERSOS Humanitarian Aid Organization","amount":1642841},{"type":"European Commission","amount":60054475},{"type":"European Commission EuropeAid Development and Cooperation","amount":13560307},{"type":"Iceland, Government of","amount":660000},{"type":"Mercy Corps","amount":2899012},{"type":"UNICEF National Committee/Sweden","amount":265076},{"type":"World Food Programme","amount":7240132},{"type":"UNICEF National Committee/Denmark","amount":14612},{"type":"UNICEF National Committee/Finland","amount":16456},{"type":"UNICEF National Committee/Turkey","amount":3308},{"type":"UNICEF National Committee/Norway","amount":689061},{"type":"European Commission Directorate General for Development","amount":162401},{"type":"Czech Republic, Government of","amount":145231},{"type":"UNICEF National Committee/Korea (Republic of)","amount":197685},{"type":"UNICEF National Committee/Switzerland","amount":26606},{"type":"Netherlands, Government of","amount":4740580},{"type":"Deutsche Gesellschaft für Internationale Zusammenarbeit","amount":3175000},{"type":"UNICEF National Committee/Hong Kong","amount":96374},{"type":"Catholic Relief Services","amount":503233},{"type":"Mexico, Government of","amount":88734},{"type":"Russian Federation, Government of","amount":500000},{"type":"Romania, Government of","amount":113250},{"type":"Oak Foundation","amount":1150000},{"type":"Norwegian Refugee Council","amount":3736548},{"type":"UN Action Against Sexual Violence in Conflict","amount":140213},{"type":"Austria, Government of","amount":1387407},{"type":"Ireland, Government of","amount":1590668}]},"clusters":[{"name":"Multi-sector","funding":1998822648,"current_requirement":5575937077}]}]}