[{"name":"Aviation","funding":6753110,"current_requirement":17000000},{"name":"Coordination","funding":1191193,"current_requirement":9500000},{"name":"Emergency Shelter and NFI","funding":5472888,"current_requirement":38092838},{"name":"Food Security and Agriculture","funding":21271999,"current_requirement":135530000},{"name":"Health","funding":2557192,"current_requirement":52492276},{"name":"Multi Sector Cash","funding":3147125,"current_requirement":95680670},{"name":"Nutrition","funding":0,"current_requirement":66500000},{"name":"Protection","funding":7832450,"current_requirement":98976653},{"name":"Water, Sanitation and Hygiene","funding":1635688,"current_requirement":36464020}]