{"highlights":{"funding_total":202613658},"appeals":[{"id":660,"source":"FTS","year":2018,"name":"Ethiopia Humanitarian and Disaster Resilience Plan 2018","type":"Humanitarian response plan","received":153101252,"required":1622539337,"percentage":9,"countries":["ETH"],"donors":{"total":153101252,"grouping":[{"type":"European Commission's Humanitarian Aid and Civil Protection Department","amount":10648221},{"type":"Central Emergency Response Fund","amount":9930695},{"type":"United States of America, Government of","amount":109548825},{"type":"Switzerland, Government of","amount":1946984},{"type":"Ireland, Government of","amount":3349693},{"type":"Japan, Government of","amount":4000000},{"type":"United Kingdom, Government of","amount":1428571},{"type":"Denmark, Government of","amount":4946702},{"type":"Sweden, Government of","amount":4441624},{"type":"Germany, Government of","amount":2859937}]},"clusters":[{"name":"Protection","funding":4301656,"current_requirement":17300000},{"name":"Agriculture and Livestock","funding":0,"current_requirement":104363825},{"name":"Nutrition","funding":1428571,"current_requirement":198255194},{"name":"Food","funding":112061509,"current_requirement":1000205764},{"name":"Water, Sanitation and Hygiene","funding":8449813,"current_requirement":99024000},{"name":"Emergency Shelter and non-food items","funding":3499420,"current_requirement":94862500},{"name":"Health","funding":586493,"current_requirement":74000000},{"name":"Education","funding":0,"current_requirement":34528054}]}]}